MANIFEST.in
README.rst
README.txt
setup.cfg
setup.py
docs/CREDITS.txt
docs/HISTORY.txt
docs/INSTALL.txt
docs/LICENSE.GPL
docs/LICENSE.txt
src/openmultimedia/__init__.py
src/openmultimedia.headband.egg-info/PKG-INFO
src/openmultimedia.headband.egg-info/SOURCES.txt
src/openmultimedia.headband.egg-info/dependency_links.txt
src/openmultimedia.headband.egg-info/entry_points.txt
src/openmultimedia.headband.egg-info/namespace_packages.txt
src/openmultimedia.headband.egg-info/not-zip-safe
src/openmultimedia.headband.egg-info/requires.txt
src/openmultimedia.headband.egg-info/top_level.txt
src/openmultimedia/headband/__init__.py
src/openmultimedia/headband/browser.py
src/openmultimedia/headband/config.py
src/openmultimedia/headband/configure.zcml
src/openmultimedia/headband/interfaces.py
src/openmultimedia/headband/testing.py
src/openmultimedia/headband/Extensions/Install.py
src/openmultimedia/headband/Extensions/__init__.py
src/openmultimedia/headband/docs/configlet.rst
src/openmultimedia/headband/docs/viewlet.rst
src/openmultimedia/headband/profiles/default/browserlayer.xml
src/openmultimedia/headband/profiles/default/controlpanel.xml
src/openmultimedia/headband/profiles/default/metadata.xml
src/openmultimedia/headband/profiles/default/registry.xml
src/openmultimedia/headband/profiles/default/viewlets.xml
src/openmultimedia/headband/profiles/testing/metadata.xml
src/openmultimedia/headband/profiles/uninstall/registry.xml
src/openmultimedia/headband/resources/header_icon.png
src/openmultimedia/headband/templates/headband.pt
src/openmultimedia/headband/tests/__init__.py
src/openmultimedia/headband/tests/test_controlpanel.py
src/openmultimedia/headband/tests/test_doctests.py
src/openmultimedia/headband/tests/test_installation.py